{
    "bigmap": {
        "zones": ["ZoneDormitory", "ZoneGasStation", "ZoneScavBase"],
        "spawnChance": 85
    },
    "factory4_day": {
        "zones": ["BotZone"],
        "spawnChance": 50
    },
    "factory4_night": {
        "zones": ["BotZone"],
        "spawnChance": 50
    },
    "interchange": {
        "zones": [
            "ZoneCenterBot",
            "ZoneCenter",
            "ZoneOLI",
            "ZoneIDEA",
            "ZoneGoshan",
            "ZoneIDEAPark",
            "ZoneOLIPark"
        ],
        "spawnChance": 75
    },
    "laboratory": {
        "zones": ["BotZoneFloor1", "BotZoneFloor2"],
        "spawnChance": 75
    },
    "lighthouse": {
        "zones": [
            "Zone_TreatmentContainers",
            "Zone_Chalet",
            "Zone_RoofContainers",
            "Zone_RoofBeach",
            "Zone_Hellicopter"
        ],
        "spawnChance": 75
    },
    "rezervbase": {
        "zones": [
            "ZoneRailStrorage",
            "ZoneRailStrorage",
            "ZoneRailStrorage",
            "ZonePTOR1",
            "ZonePTOR2",
            "ZoneBarrack",
            "ZoneBarrack",
            "ZoneBarrack",
            "ZoneSubStorage"
        ],
        "spawnChance": 75
    },
    "sandbox": {
        "zones": ["ZoneSandbox"],
        "spawnChance": 75
    },
    "sandbox_high": {
        "zones": ["ZoneSandbox"],
        "spawnChance": 75
    },
    "shoreline": {
        "zones": [
            "ZonePort",
            "ZoneGreenHouses",
            "ZoneSanatorium1",
            "ZoneGreenHouses",
            "ZoneSanatorium2",
            "ZoneMeteoStation",
            "ZoneSanatorium1",
            "ZoneSanatorium2"
        ],
        "spawnChance": 75
    },
    "tarkovstreets": {
        "zones": "ZoneColumn",
        "spawnChance": 75
    },
    "woods": {
        "zones": ["ZoneScavBase2", "ZoneWoodCutter"],
        "spawnChance": 75
    }
}
